django_salesforce_oauth/__init__.py
django_salesforce_oauth/apps.py
django_salesforce_oauth/oauth.py
django_salesforce_oauth/urls.py
django_salesforce_oauth/utils.py
django_salesforce_oauth/views.py
django_salesforce_oauth-1.0.0.dist-info/LICENSE
django_salesforce_oauth-1.0.0.dist-info/WHEEL
django_salesforce_oauth-1.0.0.dist-info/METADATA
django_salesforce_oauth-1.0.0.dist-info/RECORD
