Metadata-Version: 2.1
Name: django-salesforce-oauth
Version: 1.0.0
Summary: Simple package for creating and signing users into your Django site using Salesforce as an OAuth provider
Home-page: https://github.com/Kicksaw-Consulting/django-salesforce-oauth
License: MIT
Keywords: django,salesforce,oauth
Author: Alex Drozd
Author-email: drozdster@gmail.com
Requires-Python: >=3.8,<4.0
Classifier: License :: OSI Approved :: MIT License
Classifier: Programming Language :: Python :: 3
Classifier: Programming Language :: Python :: 3.10
Classifier: Programming Language :: Python :: 3.8
Classifier: Programming Language :: Python :: 3.9
Requires-Dist: Django (>=4.1,<5.0)
Requires-Dist: requests (>=2.24.0,<3.0.0)
Project-URL: Repository, https://github.com/Kicksaw-Consulting/django-salesforce-oauth
